mydata/__init__.py
mydata-0.1.0.dist-info/WHEEL
mydata-0.1.0.dist-info/METADATA
mydata-0.1.0.dist-info/RECORD
